Workbook

Sheet README
A1: Metals & Mining Comps Workbook
A3: Generated 2026-10-20 by metals_engine.py. To refresh: open a terminal in this folder and run: python metals_engine.py
A4: Sheets: Returns (performance since the Nov 21 2024 call) | Raw Data (statement inputs, blue = hardcoded from Yahoo Finance)
A5: Ratios (the MGT 231 framework, green = formulas linking to Raw Data) | Valuation (current multiples) | AISC (manual, from company reports)
A6: Ratios are within-company so statement currency (GBP for Fresnillo, CAD for Aya) does not distort comparisons.
A7: Data source: Yahoo Finance via the yfinance library. Verify key figures against company filings before citing.

Sheet Returns
A1: Name | B1: Ticker | C1: Price 2024-11-21 | D1: Price now | E1: As of | F1: Total return
A2: First Majestic Silver | B2: AG | C2: 6.41 | E2: 2026-10-19 | F2: =IFERROR(D2/C2-1,"n/m")
A3: Pan American Silver | B3: PAAS | C3: 22.5 | E3: 2026-10-19 | F3: =IFERROR(D3/C3-1,"n/m")
A4: Fresnillo PLC | B4: FNLPF | C4: 7.96 | D4: 35.8 | E4: 2026-10-19 | F4: =IFERROR(D4/C4-1,"n/m")
A5: Hecla Mining | B5: HL | C5: 5.67 | E5: 2026-10-19 | F5: =IFERROR(D5/C5-1,"n/m")
A6: Coeur Mining | B6: CDE | C6: 6.62 | E6: 2026-10-19 | F6: =IFERROR(D6/C6-1,"n/m")
A7: Endeavour Silver | B7: EXK | C7: 4.5 | E7: 2026-10-19 | F7: =IFERROR(D7/C7-1,"n/m")
A8: Fortuna Mining | B8: FSM | C8: 5 | E8: 2026-10-19 | F8: =IFERROR(D8/C8-1,"n/m")
A9: Silvercorp Metals | B9: SVM | C9: 3.34 | E9: 2026-10-19 | F9: =IFERROR(D9/C9-1,"n/m")
A10: Aya Gold & Silver | B10: AYA.TO | C10: 12.76 | D10: 37.4 | E10: 2026-10-19 | F10: =IFERROR(D10/C10-1,"n/m")
A11: Avino Silver & Gold | B11: ASM | C11: 1.14 | E11: 2026-10-19 | F11: =IFERROR(D11/C11-1,"n/m")
A12: Silver (spot proxy) | B12: SI=F | C12: 30.91 | D12: 57 | E12: 2026-10-19 | F12: =IFERROR(D12/C12-1,"n/m")

Sheet Raw Data
A1: All statement figures in millions of the company's reporting currency (source: Yahoo Finance)
A2: Ticker | B2: Year | C2: Revenue | D2: EBIT | E2: EBITDA | F2: NetIncome | G2: IntExp | H2: TotDebt | I2: Equity | J2: TotAssets | K2: CurAssets | L2: Inventory | M2: CurLiab | N2: FCF
A3: AG | B3: 2025 | C3: 1265.157 | D3: 409.826 | E3: 674.624 | F3: 164.923 | G3: 14.8 | H3: 308.74 | I3: 2761.005 | J3: 4694.915 | K3: 1192.701 | L3: 84.753 | M3: 459.139 | N3: 310.353
A4: AG | B4: 2024 | C4: 563.631 | D4: -11.017 | E4: 114.475 | F4: -101.885 | G4: 15.437 | H4: 237.017 | I4: 1351.071 | J4: 1979.788 | K4: 368.821 | L4: 62.524 | M4: 144.307 | N4: 36.849
A5: AG | B5: 2023 | C5: 576.385 | D5: -180.666 | E5: -54.496 | F5: -135.112 | G5: 15.249 | H5: 256.514 | I5: 1358.12 | J5: 1976.355 | K5: 309.057 | L5: 63.69 | M5: 120.138 | N5: -90.367
A6: AG | B6: 2022 | C6: 626.85 | D6: -48.463 | E6: 88.948 | F6: -114.276 | G6: 12.941 | H6: 247.945 | I6: 1411.298 | J6: 2110.009 | K6: 370.289 | L6: 64.761 | M6: 167.399 | N6: -198.692
A7: ASM | B7: 2025 | C7: 92.227 | D7: 40.214 | E7: 40.214 | F7: 26.643 | G7: 0.316 | H7: 6.014 | I7: -16.615 | J7: 279.032 | K7: 132.068 | L7: 12.196 | M7: 32.506 | N7: 1.124
A8: ASM | B8: 2024 | C8: 66.178 | D8: 14.808 | E8: 18.194 | F8: 8.1 | G8: 0.387 | H8: 2.629 | I8: -43.323 | J8: 148.711 | K8: 40.769 | L8: 7.611 | M8: 15.534 | N8: 18.669
A9: ASM | B9: 2023 | C9: 43.889 | D9: -0.129 | E9: 2.79 | F9: 0.542 | G9: 0.381 | H9: 3.454 | I9: -51.423 | J9: 128.34 | K9: 23.535 | L9: 8.826 | M9: 13.808 | N9: -5.887
A10: ASM | B10: 2022 | C10: 44.187 | D10: 7.779 | E10: 9.965 | F10: 3.096 | G10: 0.099 | H10: 6.642 | I10: 98.021 | J10: 121.196 | K10: 25.585 | L10: 6.26 | M10: 16.764 | N10: 3.995
A11: AYA.TO | B11: 2025 | C11: 202.102 | D11: 80.587 | E11: 101.112 | F11: 45.557 | G11: 10.462 | H11: 113.543 | I11: 413.651 | J11: 631.733 | K11: 232.45 | L11: 34.595 | M11: 120.05 | N11: -4.245
A12: AYA.TO | B12: 2024 | C12: 39.117 | D12: -24.648 | E12: -21.278 | F12: -21.617 | G12: 0.152 | H12: 96.92 | I12: 246.476 | J12: 400.107 | K12: 76.54 | L12: 27.389 | M12: 53.116 | N12: -101.61
A13: AYA.TO | B13: 2023 | C13: 42.849 | D13: 9.289 | E13: 14.293 | F13: 5.504 | G13: 0.073 | H13: 58.792 | I13: 220.721 | J13: 333.057 | K13: 80.399 | L13: 16.81 | M13: 46.695 | N13: -98.69
A14: AYA.TO | B14: 2022 | C14: 38.245 | D14: 4.831 | E14: 11.173 | F14: 0.466 | G14: 0.25 | H14: 0.287 | I14: 125.722 | J14: 156.804 | K14: 59.815 | L14: 7.688 | M14: 24.241 | N14: -33.666
... A42: SVM | B42: 2023 | C42: 208.129 | D42: 35.425 | E42: 64.795 | F42: 20.608 | G42: 0.282 | H42: 0.583 | I42: 489.053 | J42: 676.799 | K42: 219.048 | L42: 8.343 | M42: 41.24 | N42: 30.686

Sheet Ratios
A1: Ticker | B1: Year | C1: EBIT Margin | D1: FCF Margin | E1: Quick Ratio | F1: Debt/Capital | G1: Debt/EBITDA | H1: Interest Coverage | I1: Net Margin | J1: Asset Turnover | K1: Equity Multiplier | L1: ROE (DuPont)
A2: ='Raw Data'!A3 | B2: ='Raw Data'!B3 | C2: =IF(COUNT('Raw Data'!D3,'Raw Data'!C3)<2,"n/a",'Raw Data'!D3/'Raw Data'!C3) | D2: =IF(COUNT('Raw Data'!N3,'Raw Data'!C3)<2,"n/a",'Raw Data'!N3/'Raw Data'!C3) | E2: =IF(COUNT('Raw Data'!K3,'Raw Data'!L3,'Raw Data'!M3)<3,"n/a",('Raw Data'!K3-'Raw Data'!L3)/'Raw Data'!M3) | F2: =IF(COUNT('Raw Data'!H3,'Raw Data'!I3)<2,"n/a",'Raw Data'!H3/('Raw Data'!H3+'Raw Data'!I3)) | G2: =IF(COUNT('Raw Data'!H3,'Raw Data'!E3)<2,"n/a",IF('Raw Data'!E3<=0,"n/m",'Raw Data'!H3/'Raw Data'!E3)) | H2: =IF(COUNT('Raw Data'!D3,'Raw Data'!G3)<2,"n/a",IF('Raw Data'!G3=0,"n/m",'Raw Data'!D3/'Raw Data'!G3)) | I2: =IF(COUNT('Raw Data'!F3,'Raw Data'!C3)<2,"n/a",'Raw Data'!F3/'Raw Data'!C3) | J2: =IF(COUNT('Raw Data'!C3,'Raw Data'!J3)<2,"n/a",'Raw Data'!C3/'Raw Data'!J3) | K2: =IF(COUNT('Raw Data'!J3,'Raw Data'!I3)<2,"n/a",'Raw Data'!J3/'Raw Data'!I3) | L2: =IF(COUNT(I2,J2,K2)<3,"n/a",I2*J2*K2)
A3: ='Raw Data'!A4 | B3: ='Raw Data'!B4 | C3: =IF(COUNT('Raw Data'!D4,'Raw Data'!C4)<2,"n/a",'Raw Data'!D4/'Raw Data'!C4) | D3: =IF(COUNT('Raw Data'!N4,'Raw Data'!C4)<2,"n/a",'Raw Data'!N4/'Raw Data'!C4) | E3: =IF(COUNT('Raw Data'!K4,'Raw Data'!L4,'Raw Data'!M4)<3,"n/a",('Raw Data'!K4-'Raw Data'!L4)/'Raw Data'!M4) | F3: =IF(COUNT('Raw Data'!H4,'Raw Data'!I4)<2,"n/a",'Raw Data'!H4/('Raw Data'!H4+'Raw Data'!I4)) | G3: =IF(COUNT('Raw Data'!H4,'Raw Data'!E4)<2,"n/a",IF('Raw Data'!E4<=0,"n/m",'Raw Data'!H4/'Raw Data'!E4)) | H3: =IF(COUNT('Raw Data'!D4,'Raw Data'!G4)<2,"n/a",IF('Raw Data'!G4=0,"n/m",'Raw Data'!D4/'Raw Data'!G4)) | I3: =IF(COUNT('Raw Data'!F4,'Raw Data'!C4)<2,"n/a",'Raw Data'!F4/'Raw Data'!C4) | J3: =IF(COUNT('Raw Data'!C4,'Raw Data'!J4)<2,"n/a",'Raw Data'!C4/'Raw Data'!J4) | K3: =IF(COUNT('Raw Data'!J4,'Raw Data'!I4)<2,"n/a",'Raw Data'!J4/'Raw Data'!I4) | L3: =IF(COUNT(I3,J3,K3)<3,"n/a",I3*J3*K3)
A4: ='Raw Data'!A5 | B4: ='Raw Data'!B5 | C4: =IF(COUNT('Raw Data'!D5,'Raw Data'!C5)<2,"n/a",'Raw Data'!D5/'Raw Data'!C5) | D4: =IF(COUNT('Raw Data'!N5,'Raw Data'!C5)<2,"n/a",'Raw Data'!N5/'Raw Data'!C5) | E4: =IF(COUNT('Raw Data'!K5,'Raw Data'!L5,'Raw Data'!M5)<3,"n/a",('Raw Data'!K5-'Raw Data'!L5)/'Raw Data'!M5) | F4: =IF(COUNT('Raw Data'!H5,'Raw Data'!I5)<2,"n/a",'Raw Data'!H5/('Raw Data'!H5+'Raw Data'!I5)) | G4: =IF(COUNT('Raw Data'!H5,'Raw Data'!E5)<2,"n/a",IF('Raw Data'!E5<=0,"n/m",'Raw Data'!H5/'Raw Data'!E5)) | H4: =IF(COUNT('Raw Data'!D5,'Raw Data'!G5)<2,"n/a",IF('Raw Data'!G5=0,"n/m",'Raw Data'!D5/'Raw Data'!G5)) | I4: =IF(COUNT('Raw Data'!F5,'Raw Data'!C5)<2,"n/a",'Raw Data'!F5/'Raw Data'!C5) | J4: =IF(COUNT('Raw Data'!C5,'Raw Data'!J5)<2,"n/a",'Raw Data'!C5/'Raw Data'!J5) | K4: =IF(COUNT('Raw Data'!J5,'Raw Data'!I5)<2,"n/a",'Raw Data'!J5/'Raw Data'!I5) | L4: =IF(COUNT(I4,J4,K4)<3,"n/a",I4*J4*K4)
A5: ='Raw Data'!A6 | B5: ='Raw Data'!B6 | C5: =IF(COUNT('Raw Data'!D6,'Raw Data'!C6)<2,"n/a",'Raw Data'!D6/'Raw Data'!C6) | D5: =IF(COUNT('Raw Data'!N6,'Raw Data'!C6)<2,"n/a",'Raw Data'!N6/'Raw Data'!C6) | E5: =IF(COUNT('Raw Data'!K6,'Raw Data'!L6,'Raw Data'!M6)<3,"n/a",('Raw Data'!K6-'Raw Data'!L6)/'Raw Data'!M6) | F5: =IF(COUNT('Raw Data'!H6,'Raw Data'!I6)<2,"n/a",'Raw Data'!H6/('Raw Data'!H6+'Raw Data'!I6)) | G5: =IF(COUNT('Raw Data'!H6,'Raw Data'!E6)<2,"n/a",IF('Raw Data'!E6<=0,"n/m",'Raw Data'!H6/'Raw Data'!E6)) | H5: =IF(COUNT('Raw Data'!D6,'Raw Data'!G6)<2,"n/a",IF('Raw Data'!G6=0,"n/m",'Raw Data'!D6/'Raw Data'!G6)) | I5: =IF(COUNT('Raw Data'!F6,'Raw Data'!C6)<2,"n/a",'Raw Data'!F6/'Raw Data'!C6) | J5: =IF(COUNT('Raw Data'!C6,'Raw Data'!J6)<2,"n/a",'Raw Data'!C6/'Raw Data'!J6) | K5: =IF(COUNT('Raw Data'!J6,'Raw Data'!I6)<2,"n/a",'Raw Data'!J6/'Raw Data'!I6) | L5: =IF(COUNT(I5,J5,K5)<3,"n/a",I5*J5*K5)
A6: ='Raw Data'!A7 | B6: ='Raw Data'!B7 | C6: =IF(COUNT('Raw Data'!D7,'Raw Data'!C7)<2,"n/a",'Raw Data'!D7/'Raw Data'!C7) | D6: =IF(COUNT('Raw Data'!N7,'Raw Data'!C7)<2,"n/a",'Raw Data'!N7/'Raw Data'!C7) | E6: =IF(COUNT('Raw Data'!K7,'Raw Data'!L7,'Raw Data'!M7)<3,"n/a",('Raw Data'!K7-'Raw Data'!L7)/'Raw Data'!M7) | F6: =IF(COUNT('Raw Data'!H7,'Raw Data'!I7)<2,"n/a",'Raw Data'!H7/('Raw Data'!H7+'Raw Data'!I7)) | G6: =IF(COUNT('Raw Data'!H7,'Raw Data'!E7)<2,"n/a",IF('Raw Data'!E7<=0,"n/m",'Raw Data'!H7/'Raw Data'!E7)) | H6: =IF(COUNT('Raw Data'!D7,'Raw Data'!G7)<2,"n/a",IF('Raw Data'!G7=0,"n/m",'Raw Data'!D7/'Raw Data'!G7)) | I6: =IF(COUNT('Raw Data'!F7,'Raw Data'!C7)<2,"n/a",'Raw Data'!F7/'Raw Data'!C7) | J6: =IF(COUNT('Raw Data'!C7,'Raw Data'!J7)<2,"n/a",'Raw Data'!C7/'Raw Data'!J7) | K6: =IF(COUNT('Raw Data'!J7,'Raw Data'!I7)<2,"n/a",'Raw Data'!J7/'Raw Data'!I7) | L6: =IF(COUNT(I6,J6,K6)<3,"n/a",I6*J6*K6)
A7: ='Raw Data'!A8 | B7: ='Raw Data'!B8 | C7: =IF(COUNT('Raw Data'!D8,'Raw Data'!C8)<2,"n/a",'Raw Data'!D8/'Raw Data'!C8) | D7: =IF(COUNT('Raw Data'!N8,'Raw Data'!C8)<2,"n/a",'Raw Data'!N8/'Raw Data'!C8) | E7: =IF(COUNT('Raw Data'!K8,'Raw Data'!L8,'Raw Data'!M8)<3,"n/a",('Raw Data'!K8-'Raw Data'!L8)/'Raw Data'!M8) | F7: =IF(COUNT('Raw Data'!H8,'Raw Data'!I8)<2,"n/a",'Raw Data'!H8/('Raw Data'!H8+'Raw Data'!I8)) | G7: =IF(COUNT('Raw Data'!H8,'Raw Data'!E8)<2,"n/a",IF('Raw Data'!E8<=0,"n/m",'Raw Data'!H8/'Raw Data'!E8)) | H7: =IF(COUNT('Raw Data'!D8,'Raw Data'!G8)<2,"n/a",IF('Raw Data'!G8=0,"n/m",'Raw Data'!D8/'Raw Data'!G8)) | I7: =IF(COUNT('Raw Data'!F8,'Raw Data'!C8)<2,"n/a",'Raw Data'!F8/'Raw Data'!C8) | J7: =IF(COUNT('Raw Data'!C8,'Raw Data'!J8)<2,"n/a",'Raw Data'!C8/'Raw Data'!J8) | K7: =IF(COUNT('Raw Data'!J8,'Raw Data'!I8)<2,"n/a",'Raw Data'!J8/'Raw Data'!I8) | L7: =IF(COUNT(I7,J7,K7)<3,"n/a",I7*J7*K7)
A8: ='Raw Data'!A9 | B8: ='Raw Data'!B9 | C8: =IF(COUNT('Raw Data'!D9,'Raw Data'!C9)<2,"n/a",'Raw Data'!D9/'Raw Data'!C9) | D8: =IF(COUNT('Raw Data'!N9,'Raw Data'!C9)<2,"n/a",'Raw Data'!N9/'Raw Data'!C9) | E8: =IF(COUNT('Raw Data'!K9,'Raw Data'!L9,'Raw Data'!M9)<3,"n/a",('Raw Data'!K9-'Raw Data'!L9)/'Raw Data'!M9) | F8: =IF(COUNT('Raw Data'!H9,'Raw Data'!I9)<2,"n/a",'Raw Data'!H9/('Raw Data'!H9+'Raw Data'!I9)) | G8: =IF(COUNT('Raw Data'!H9,'Raw Data'!E9)<2,"n/a",IF('Raw Data'!E9<=0,"n/m",'Raw Data'!H9/'Raw Data'!E9)) | H8: =IF(COUNT('Raw Data'!D9,'Raw Data'!G9)<2,"n/a",IF('Raw Data'!G9=0,"n/m",'Raw Data'!D9/'Raw Data'!G9)) | I8: =IF(COUNT('Raw Data'!F9,'Raw Data'!C9)<2,"n/a",'Raw Data'!F9/'Raw Data'!C9) | J8: =IF(COUNT('Raw Data'!C9,'Raw Data'!J9)<2,"n/a",'Raw Data'!C9/'Raw Data'!J9) | K8: =IF(COUNT('Raw Data'!J9,'Raw Data'!I9)<2,"n/a",'Raw Data'!J9/'Raw Data'!I9) | L8: =IF(COUNT(I8,J8,K8)<3,"n/a",I8*J8*K8)
A9: ='Raw Data'!A10 | B9: ='Raw Data'!B10 | C9: =IF(COUNT('Raw Data'!D10,'Raw Data'!C10)<2,"n/a",'Raw Data'!D10/'Raw Data'!C10) | D9: =IF(COUNT('Raw Data'!N10,'Raw Data'!C10)<2,"n/a",'Raw Data'!N10/'Raw Data'!C10) | E9: =IF(COUNT('Raw Data'!K10,'Raw Data'!L10,'Raw Data'!M10)<3,"n/a",('Raw Data'!K10-'Raw Data'!L10)/'Raw Data'!M10) | F9: =IF(COUNT('Raw Data'!H10,'Raw Data'!I10)<2,"n/a",'Raw Data'!H10/('Raw Data'!H10+'Raw Data'!I10)) | G9: =IF(COUNT('Raw Data'!H10,'Raw Data'!E10)<2,"n/a",IF('Raw Data'!E10<=0,"n/m",'Raw Data'!H10/'Raw Data'!E10)) | H9: =IF(COUNT('Raw Data'!D10,'Raw Data'!G10)<2,"n/a",IF('Raw Data'!G10=0,"n/m",'Raw Data'!D10/'Raw Data'!G10)) | I9: =IF(COUNT('Raw Data'!F10,'Raw Data'!C10)<2,"n/a",'Raw Data'!F10/'Raw Data'!C10) | J9: =IF(COUNT('Raw Data'!C10,'Raw Data'!J10)<2,"n/a",'Raw Data'!C10/'Raw Data'!J10) | K9: =IF(COUNT('Raw Data'!J10,'Raw Data'!I10)<2,"n/a",'Raw Data'!J10/'Raw Data'!I10) | L9: =IF(COUNT(I9,J9,K9)<3,"n/a",I9*J9*K9)
A10: ='Raw Data'!A11 | B10: ='Raw Data'!B11 | C10: =IF(COUNT('Raw Data'!D11,'Raw Data'!C11)<2,"n/a",'Raw Data'!D11/'Raw Data'!C11) | D10: =IF(COUNT('Raw Data'!N11,'Raw Data'!C11)<2,"n/a",'Raw Data'!N11/'Raw Data'!C11) | E10: =IF(COUNT('Raw Data'!K11,'Raw Data'!L11,'Raw Data'!M11)<3,"n/a",('Raw Data'!K11-'Raw Data'!L11)/'Raw Data'!M11) | F10: =IF(COUNT('Raw Data'!H11,'Raw Data'!I11)<2,"n/a",'Raw Data'!H11/('Raw Data'!H11+'Raw Data'!I11)) | G10: =IF(COUNT('Raw Data'!H11,'Raw Data'!E11)<2,"n/a",IF('Raw Data'!E11<=0,"n/m",'Raw Data'!H11/'Raw Data'!E11)) | H10: =IF(COUNT('Raw Data'!D11,'Raw Data'!G11)<2,"n/a",IF('Raw Data'!G11=0,"n/m",'Raw Data'!D11/'Raw Data'!G11)) | I10: =IF(COUNT('Raw Data'!F11,'Raw Data'!C11)<2,"n/a",'Raw Data'!F11/'Raw Data'!C11) | J10: =IF(COUNT('Raw Data'!C11,'Raw Data'!J11)<2,"n/a",'Raw Data'!C11/'Raw Data'!J11) | K10: =IF(COUNT('Raw Data'!J11,'Raw Data'!I11)<2,"n/a",'Raw Data'!J11/'Raw Data'!I11) | L10: =IF(COUNT(I10,J10,K10)<3,"n/a",I10*J10*K10)
A11: ='Raw Data'!A12 | B11: ='Raw Data'!B12 | C11: =IF(COUNT('Raw Data'!D12,'Raw Data'!C12)<2,"n/a",'Raw Data'!D12/'Raw Data'!C12) | D11: =IF(COUNT('Raw Data'!N12,'Raw Data'!C12)<2,"n/a",'Raw Data'!N12/'Raw Data'!C12) | E11: =IF(COUNT('Raw Data'!K12,'Raw Data'!L12,'Raw Data'!M12)<3,"n/a",('Raw Data'!K12-'Raw Data'!L12)/'Raw Data'!M12) | F11: =IF(COUNT('Raw Data'!H12,'Raw Data'!I12)<2,"n/a",'Raw Data'!H12/('Raw Data'!H12+'Raw Data'!I12)) | G11: =IF(COUNT('Raw Data'!H12,'Raw Data'!E12)<2,"n/a",IF('Raw Data'!E12<=0,"n/m",'Raw Data'!H12/'Raw Data'!E12)) | H11: =IF(COUNT('Raw Data'!D12,'Raw Data'!G12)<2,"n/a",IF('Raw Data'!G12=0,"n/m",'Raw Data'!D12/'Raw Data'!G12)) | I11: =IF(COUNT('Raw Data'!F12,'Raw Data'!C12)<2,"n/a",'Raw Data'!F12/'Raw Data'!C12) | J11: =IF(COUNT('Raw Data'!C12,'Raw Data'!J12)<2,"n/a",'Raw Data'!C12/'Raw Data'!J12) | K11: =IF(COUNT('Raw Data'!J12,'Raw Data'!I12)<2,"n/a",'Raw Data'!J12/'Raw Data'!I12) | L11: =IF(COUNT(I11,J11,K11)<3,"n/a",I11*J11*K11)
A12: ='Raw Data'!A13 | B12: ='Raw Data'!B13 | C12: =IF(COUNT('Raw Data'!D13,'Raw Data'!C13)<2,"n/a",'Raw Data'!D13/'Raw Data'!C13) | D12: =IF(COUNT('Raw Data'!N13,'Raw Data'!C13)<2,"n/a",'Raw Data'!N13/'Raw Data'!C13) | E12: =IF(COUNT('Raw Data'!K13,'Raw Data'!L13,'Raw Data'!M13)<3,"n/a",('Raw Data'!K13-'Raw Data'!L13)/'Raw Data'!M13) | F12: =IF(COUNT('Raw Data'!H13,'Raw Data'!I13)<2,"n/a",'Raw Data'!H13/('Raw Data'!H13+'Raw Data'!I13)) | G12: =IF(COUNT('Raw Data'!H13,'Raw Data'!E13)<2,"n/a",IF('Raw Data'!E13<=0,"n/m",'Raw Data'!H13/'Raw Data'!E13)) | H12: =IF(COUNT('Raw Data'!D13,'Raw Data'!G13)<2,"n/a",IF('Raw Data'!G13=0,"n/m",'Raw Data'!D13/'Raw Data'!G13)) | I12: =IF(COUNT('Raw Data'!F13,'Raw Data'!C13)<2,"n/a",'Raw Data'!F13/'Raw Data'!C13) | J12: =IF(COUNT('Raw Data'!C13,'Raw Data'!J13)<2,"n/a",'Raw Data'!C13/'Raw Data'!J13) | K12: =IF(COUNT('Raw Data'!J13,'Raw Data'!I13)<2,"n/a",'Raw Data'!J13/'Raw Data'!I13) | L12: =IF(COUNT(I12,J12,K12)<3,"n/a",I12*J12*K12)
A13: ='Raw Data'!A14 | B13: ='Raw Data'!B14 | C13: =IF(COUNT('Raw Data'!D14,'Raw Data'!C14)<2,"n/a",'Raw Data'!D14/'Raw Data'!C14) | D13: =IF(COUNT('Raw Data'!N14,'Raw Data'!C14)<2,"n/a",'Raw Data'!N14/'Raw Data'!C14) | E13: =IF(COUNT('Raw Data'!K14,'Raw Data'!L14,'Raw Data'!M14)<3,"n/a",('Raw Data'!K14-'Raw Data'!L14)/'Raw Data'!M14) | F13: =IF(COUNT('Raw Data'!H14,'Raw Data'!I14)<2,"n/a",'Raw Data'!H14/('Raw Data'!H14+'Raw Data'!I14)) | G13: =IF(COUNT('Raw Data'!H14,'Raw Data'!E14)<2,"n/a",IF('Raw Data'!E14<=0,"n/m",'Raw Data'!H14/'Raw Data'!E14)) | H13: =IF(COUNT('Raw Data'!D14,'Raw Data'!G14)<2,"n/a",IF('Raw Data'!G14=0,"n/m",'Raw Data'!D14/'Raw Data'!G14)) | I13: =IF(COUNT('Raw Data'!F14,'Raw Data'!C14)<2,"n/a",'Raw Data'!F14/'Raw Data'!C14) | J13: =IF(COUNT('Raw Data'!C14,'Raw Data'!J14)<2,"n/a",'Raw Data'!C14/'Raw Data'!J14) | K13: =IF(COUNT('Raw Data'!J14,'Raw Data'!I14)<2,"n/a",'Raw Data'!J14/'Raw Data'!I14) | L13: =IF(COUNT(I13,J13,K13)<3,"n/a",I13*J13*K13)
... A41: ='Raw Data'!A42 | B41: ='Raw Data'!B42 | C41: =IF(COUNT('Raw Data'!D42,'Raw Data'!C42)<2,"n/a",'Raw Data'!D42/'Raw Data'!C42) | D41: =IF(COUNT('Raw Data'!N42,'Raw Data'!C42)<2,"n/a",'Raw Data'!N42/'Raw Data'!C42) | E41: =IF(COUNT('Raw Data'!K42,'Raw Data'!L42,'Raw Data'!M42)<3,"n/a",('Raw Data'!K42-'Raw Data'!L42)/'Raw Data'!M42) | F41: =IF(COUNT('Raw Data'!H42,'Raw Data'!I42)<2,"n/a",'Raw Data'!H42/('Raw Data'!H42+'Raw Data'!I42)) | G41: =IF(COUNT('Raw Data'!H42,'Raw Data'!E42)<2,"n/a",IF('Raw Data'!E42<=0,"n/m",'Raw Data'!H42/'Raw Data'!E42)) | H41: =IF(COUNT('Raw Data'!D42,'Raw Data'!G42)<2,"n/a",IF('Raw Data'!G42=0,"n/m",'Raw Data'!D42/'Raw Data'!G42)) | I41: =IF(COUNT('Raw Data'!F42,'Raw Data'!C42)<2,"n/a",'Raw Data'!F42/'Raw Data'!C42) | J41: =IF(COUNT('Raw Data'!C42,'Raw Data'!J42)<2,"n/a",'Raw Data'!C42/'Raw Data'!J42) | K41: =IF(COUNT('Raw Data'!J42,'Raw Data'!I42)<2,"n/a",'Raw Data'!J42/'Raw Data'!I42) | L41: =IF(COUNT(I41,J41,K41)<3,"n/a",I41*J41*K41)

Sheet Valuation
A1: Snapshot 2026-10-20 — listed-currency figures from Yahoo Finance
A2: Name | B2: Ticker | C2: Price | D2: Mkt Cap ($mm) | E2: Book Value/sh | F2: EV ($mm) | G2: Trailing EBITDA ($mm) | H2: P/B | I2: EV/EBITDA
A3: First Majestic Silver | B3: AG | C3: 15.98 | D3: 7879.4327 | E3: 6.02 | F3: 7368.6641 | G3: 942.21197 | H3: =IFERROR(C3/E3,"n/m") | I3: =IF(G3<=0,"n/m",F3/G3)
A4: Pan American Silver | B4: PAAS | C4: 44.43 | D4: 18421.477 | E4: 17.642 | F4: 17668.598 | G4: 2124 | H4: =IFERROR(C4/E4,"n/m") | I4: =IF(G4<=0,"n/m",F4/G4)
A5: Fresnillo PLC | B5: FNLPF | C5: 35.8 | D5: 26380.79 | E5: 6.95 | F5: 25154.13 | G5: 4027.734 | H5: =IFERROR(C5/E5,"n/m") | I5: =IF(G5<=0,"n/m",F5/G5)
A6: Hecla Mining | B6: HL | C6: 15.05 | D6: 10110.115 | E6: 3.986 | F6: 9646.2909 | G6: 969.48499 | H6: =IFERROR(C6/E6,"n/m") | I6: =IF(G6<=0,"n/m",F6/G6)
A7: Coeur Mining | B7: CDE | C7: 15.33 | D7: 15758.243 | E7: 10.121 | F7: 15419.126 | G7: 1629.442 | H7: =IFERROR(C7/E7,"n/m") | I7: =IF(G7<=0,"n/m",F7/G7)
A8: Endeavour Silver | B8: EXK | C8: 8.26 | D8: 2446.1535 | E8: 2.406 | F8: 2450.9535 | G8: 281.5 | H8: =IFERROR(C8/E8,"n/m") | I8: =IF(G8<=0,"n/m",F8/G8)
A9: Fortuna Mining | B9: FSM | C9: 10.59 | D9: 3134.1885 | E9: 5.97 | F9: 2805.9208 | G9: 750.46003 | H9: =IFERROR(C9/E9,"n/m") | I9: =IF(G9<=0,"n/m",F9/G9)
A10: Silvercorp Metals | B10: SVM | C10: 9.77 | D10: 2161.1858 | E10: 4.461 | F10: 2088.9016 | G10: 309.13901 | H10: =IFERROR(C10/E10,"n/m") | I10: =IF(G10<=0,"n/m",F10/G10)
A11: Aya Gold & Silver | B11: AYA.TO | C11: 37.4 | D11: 5386.9527 | E11: 4.8058186 | F11: 5301.0248 | G11: 207.97299 | H11: =IFERROR(C11/E11,"n/m") | I11: =IF(G11<=0,"n/m",F11/G11)
A12: Avino Silver & Gold | B12: ASM | C12: 5.21 | D12: 884.94592 | E12: 1.664 | F12: 748.6681 | G12: 57.053 | H12: =IFERROR(C12/E12,"n/m") | I12: =IF(G12<=0,"n/m",F12/G12)

Sheet AISC
A1: AISC per silver-equivalent ounce (US$) — manual inputs from company press releases; yellow = fill in
A2: Company | B2: FY2025 AISC $/AgEq oz | C2: Source
A3: First Majestic Silver | B3: 21.17 | C3: FY2025 results press release, firstmajestic.com
A4: Pan American Silver
A5: Fresnillo PLC
A6: Hecla Mining
A7: Coeur Mining
A8: Endeavour Silver
A9: Fortuna Mining
A10: Silvercorp Metals
A11: Aya Gold & Silver
A12: Avino Silver & Gold
