Workbook

Sheet README
A1: First Majestic Silver — Net Asset Value model
A3: WHAT THIS IS: each producing mine is a mini-DCF — project production, price it with the silver/gold deck,
A4: subtract all-in sustaining costs and tax, discount each year's cash flow, sum. Add net cash, subtract
A5: corporate overhead, divide by shares = NAV per share. Compare to the market price = P/NAV.
A7: HOW TO USE: everything you might change lives on the Assumptions sheet. Yellow = judgment calls to own.
A8: Blue = hardcoded facts from disclosures. Black/green = formulas. Change the deck number or discount rate
A9: and the whole model reprices instantly.
A11: KEY SIMPLIFICATIONS (know these for interviews):
A12: 1. Flat production over each mine's modeled life (real mines have grade/throughput profiles).
A13: 2. AISC used as the all-in cost proxy — it includes sustaining capex but NOT expansionary capex
A14: (company guides $154-171M expansionary in 2026 alone). NAV is optimistic by roughly that PV.
A15: 3. Mine life = reserve life + a judgment 'resource conversion' extension. Defend the extension years.
... A27: spot Ag ~$61 / Au ~$4,120 (Jul 2, 2026); decks bracket HSBC / spot / JPM-GS style forecasts.

Sheet NAV
A1: Net Asset Value — summary
A3: Asset | B3: NPV ($mm)
A4: San Dimas | B4: ='San Dimas'!B20
A5: Santa Elena | B5: ='Santa Elena'!B20
A6: Los Gatos (70%) | B6: ='Los Gatos 70'!B20
A7: La Encantada | B7: ='La Encantada'!B20
A8: Jerritt Canyon (× include toggle) | B8: =JerrittCanyon!B17*Assumptions!B24
A9: Mining NAV | B9: =SUM(B4:B8)
A11: Less: PV of corporate G&A (annuity) | B11: =-Assumptions!B21*(1-(1+Assumptions!B16)^-Assumptions!B22)/Assumptions!B16
A12: Plus: net cash (Q1 2026) | B12: =Assumptions!B20
A13: Corporate NAV | B13: =B9+B11+B12
A15: Shares outstanding (M) | B15: =Assumptions!B19
A16: NAV per share (US$) | B16: =B13/B15
A17: Current price (US$) | B17: =Assumptions!B23
A18: P/NAV | B18: =B17/B16
A19: Implied upside/(downside) to NAV | B19: =B16/B17-1

Sheet Assumptions
A1: Assumptions — yellow cells are yours to defend
A3: Selected price deck (1=Conservative, 2=Spot-flat, 3=Bull) | B3: 2
A5: Price decks (US$/oz) | D5: 2026 | E5: 2027 | F5: 2028 | G5: 2029 | H5: 2030 | I5: 2031 | J5: 2032 | K5: 2033 | L5: 2034 | M5: 2035
A6: Silver: Deck 1 — Conservative (bank-fade) | D6: 55 | E6: 50 | F6: 47 | G6: 45 | H6: 45 | I6: 45 | J6: 45 | K6: 45 | L6: 45 | M6: 45
A7: Silver: Deck 2 — Spot-anchored flat | D7: 61 | E7: 61 | F7: 61 | G7: 61 | H7: 61 | I7: 61 | J7: 61 | K7: 61 | L7: 61 | M7: 61
A8: Silver: Deck 3 — Structural bull | D8: 62 | E8: 72 | F8: 80 | G8: 75 | H8: 70 | I8: 70 | J8: 70 | K8: 70 | L8: 70 | M8: 70
A9: Silver price USED (per selected deck) | D9: =CHOOSE($B$3,D6,D7,D8) | E9: =CHOOSE($B$3,E6,E7,E8) | F9: =CHOOSE($B$3,F6,F7,F8) | G9: =CHOOSE($B$3,G6,G7,G8) | H9: =CHOOSE($B$3,H6,H7,H8) | I9: =CHOOSE($B$3,I6,I7,I8) | J9: =CHOOSE($B$3,J6,J7,J8) | K9: =CHOOSE($B$3,K6,K7,K8) | ... M9: =CHOOSE($B$3,M6,M7,M8)
A11: Gold: Deck 1 — Conservative (bank-fade) | D11: 4000 | E11: 3800 | F11: 3600 | G11: 3500 | H11: 3500 | I11: 3500 | J11: 3500 | K11: 3500 | L11: 3500 | M11: 3500
A12: Gold: Deck 2 — Spot-anchored flat | D12: 4120 | E12: 4120 | F12: 4120 | G12: 4120 | H12: 4120 | I12: 4120 | J12: 4120 | K12: 4120 | L12: 4120 | M12: 4120
A13: Gold: Deck 3 — Structural bull | D13: 4200 | E13: 4500 | F13: 4800 | G13: 4500 | H13: 4400 | I13: 4400 | J13: 4400 | K13: 4400 | L13: 4400 | M13: 4400
A14: Gold price USED (per selected deck) | D14: =CHOOSE($B$3,D11,D12,D13) | E14: =CHOOSE($B$3,E11,E12,E13) | F14: =CHOOSE($B$3,F11,F12,F13) | G14: =CHOOSE($B$3,G11,G12,G13) | H14: =CHOOSE($B$3,H11,H12,H13) | I14: =CHOOSE($B$3,I11,I12,I13) | J14: =CHOOSE($B$3,J11,J12,J13) | K14: =CHOOSE($B$3,K11,K12,K13) | ... M14: =CHOOSE($B$3,M11,M12,M13)
A16: Discount rate (NAV convention: 5% for precious) | B16: 0.05
A17: Tax rate — Mexico (income + mining duties, effective) | B17: 0.4
A18: Tax rate — US / Nevada (effective) | B18: 0.25
A19: Shares outstanding (M) | B19: 488.7
A20: Net cash, Q1 2026 ($mm) = 984.8 - 297.4 | B20: 687.4
A21: Corporate G&A ($mm/yr) | B21: 60
A22: G&A years capitalized | B22: 10
A23: Current share price (US$, Jul 2 2026) | B23: 17.42
A24: Include Jerritt Canyon? (1=yes, 0=no) | B24: 1
A27: Mine parameters
A28: Mine | B28: Ag Moz/yr | C28: Au koz/yr | D28: Byprod AgEq Moz/yr | E28: AISC $/AgEq oz | F28: P&P reserves attrib (AgEq Moz) | G28: Reserve life (yrs) | H28: + Conversion yrs (judgment) | I28: Modeled life (yrs)
A29: San Dimas | B29: 4.2 | C29: 52 | D29: 0 | E29: 25.5 | F29: 22 | G29: =F29/(B29+C29/1000*67.5+D29) | H29: 3 | I29: =ROUND(G29,0)+H29
A30: Santa Elena | B30: 1.4 | C30: 67.5 | D30: 0 | E30: 25.7 | F30: 48.4 | G30: =F30/(B30+C30/1000*67.5+D30) | H30: 2 | I30: =ROUND(G30,0)+H30
A31: Los Gatos (70%) | B31: 5.1 | C31: 3 | D31: 3 | E31: 18.5 | F31: 55.3 | G31: =F31/(B31+C31/1000*67.5+D31) | H31: 3 | I31: =ROUND(G31,0)+H31
A32: La Encantada | B32: 2.95 | C32: 0 | D32: 0.2 | E32: 31.5 | F32: 13.5 | G32: =F32/(B32+C32/1000*67.5+D32) | H32: 1 | I32: =ROUND(G32,0)+H32
A34: Jerritt Canyon restart case (update after Q4 2026 pre-feasibility study)
A35: Gold production (koz/yr) | B35: 120
A36: AISC ($/Au oz) | B36: 1900
A37: First production year | B37: 2028
A38: Production years modeled | B38: 8
A39: Restart capex 2026 ($mm) | B39: 40
A40: Restart capex 2027 ($mm) | B40: 35

Sheet San Dimas
A1: San Dimas — mini-DCF
A3: Year | D3: 2026 | E3: 2027 | F3: 2028 | G3: 2029 | H3: 2030 | I3: 2031 | J3: 2032 | K3: 2033 | L3: 2034 | M3: 2035
A4: t | D4: 1 | E4: 2 | F4: 3 | G4: 4 | H4: 5 | I4: 6 | J4: 7 | K4: 8 | L4: 9 | M4: 10
A5: Active (1/0) | D5: =IF(D4<=Assumptions!$I$29,1,0) | E5: =IF(E4<=Assumptions!$I$29,1,0) | F5: =IF(F4<=Assumptions!$I$29,1,0) | G5: =IF(G4<=Assumptions!$I$29,1,0) | H5: =IF(H4<=Assumptions!$I$29,1,0) | I5: =IF(I4<=Assumptions!$I$29,1,0) | J5: =IF(J4<=Assumptions!$I$29,1,0) | K5: =IF(K4<=Assumptions!$I$29,1,0) | ... M5: =IF(M4<=Assumptions!$I$29,1,0)
A6: Ag prod (Moz) | D6: =Assumptions!$B$29*D5 | E6: =Assumptions!$B$29*E5 | F6: =Assumptions!$B$29*F5 | G6: =Assumptions!$B$29*G5 | H6: =Assumptions!$B$29*H5 | I6: =Assumptions!$B$29*I5 | J6: =Assumptions!$B$29*J5 | K6: =Assumptions!$B$29*K5 | ... M6: =Assumptions!$B$29*M5
A7: Au prod (koz) | D7: =Assumptions!$C$29*D5 | E7: =Assumptions!$C$29*E5 | F7: =Assumptions!$C$29*F5 | G7: =Assumptions!$C$29*G5 | H7: =Assumptions!$C$29*H5 | I7: =Assumptions!$C$29*I5 | J7: =Assumptions!$C$29*J5 | K7: =Assumptions!$C$29*K5 | ... M7: =Assumptions!$C$29*M5
A8: Byprod AgEq (Moz) | D8: =Assumptions!$D$29*D5 | E8: =Assumptions!$D$29*E5 | F8: =Assumptions!$D$29*F5 | G8: =Assumptions!$D$29*G5 | H8: =Assumptions!$D$29*H5 | I8: =Assumptions!$D$29*I5 | J8: =Assumptions!$D$29*J5 | K8: =Assumptions!$D$29*K5 | ... M8: =Assumptions!$D$29*M5
A9: Ag price | D9: =Assumptions!D$9 | E9: =Assumptions!E$9 | F9: =Assumptions!F$9 | G9: =Assumptions!G$9 | H9: =Assumptions!H$9 | I9: =Assumptions!I$9 | J9: =Assumptions!J$9 | K9: =Assumptions!K$9 | ... M9: =Assumptions!M$9
A10: Au price | D10: =Assumptions!D$14 | E10: =Assumptions!E$14 | F10: =Assumptions!F$14 | G10: =Assumptions!G$14 | H10: =Assumptions!H$14 | I10: =Assumptions!I$14 | J10: =Assumptions!J$14 | K10: =Assumptions!K$14 | ... M10: =Assumptions!M$14
A11: AgEq total (Moz) | D11: =D6+D7/1000*D10/D9+D8 | E11: =E6+E7/1000*E10/E9+E8 | F11: =F6+F7/1000*F10/F9+F8 | G11: =G6+G7/1000*G10/G9+G8 | H11: =H6+H7/1000*H10/H9+H8 | I11: =I6+I7/1000*I10/I9+I8 | J11: =J6+J7/1000*J10/J9+J8 | K11: =K6+K7/1000*K10/K9+K8 | ... M11: =M6+M7/1000*M10/M9+M8
A12: Revenue ($mm) | D12: =D6*D9+D7/1000*D10+D8*D9 | E12: =E6*E9+E7/1000*E10+E8*E9 | F12: =F6*F9+F7/1000*F10+F8*F9 | G12: =G6*G9+G7/1000*G10+G8*G9 | H12: =H6*H9+H7/1000*H10+H8*H9 | I12: =I6*I9+I7/1000*I10+I8*I9 | J12: =J6*J9+J7/1000*J10+J8*J9 | K12: =K6*K9+K7/1000*K10+K8*K9 | ... M12: =M6*M9+M7/1000*M10+M8*M9
A13: AISC cost ($mm) | D13: =Assumptions!$E$29*D11 | E13: =Assumptions!$E$29*E11 | F13: =Assumptions!$E$29*F11 | G13: =Assumptions!$E$29*G11 | H13: =Assumptions!$E$29*H11 | I13: =Assumptions!$E$29*I11 | J13: =Assumptions!$E$29*J11 | K13: =Assumptions!$E$29*K11 | ... M13: =Assumptions!$E$29*M11
A14: Pre-tax CF ($mm) | D14: =D12-D13 | E14: =E12-E13 | F14: =F12-F13 | G14: =G12-G13 | H14: =H12-H13 | I14: =I12-I13 | J14: =J12-J13 | K14: =K12-K13 | ... M14: =M12-M13
A15: Tax ($mm) | D15: =MAX(0,D14*Assumptions!$B$17) | E15: =MAX(0,E14*Assumptions!$B$17) | F15: =MAX(0,F14*Assumptions!$B$17) | G15: =MAX(0,G14*Assumptions!$B$17) | H15: =MAX(0,H14*Assumptions!$B$17) | I15: =MAX(0,I14*Assumptions!$B$17) | J15: =MAX(0,J14*Assumptions!$B$17) | K15: =MAX(0,K14*Assumptions!$B$17) | ... M15: =MAX(0,M14*Assumptions!$B$17)
A16: After-tax CF ($mm) | D16: =D14-D15 | E16: =E14-E15 | F16: =F14-F15 | G16: =G14-G15 | H16: =H14-H15 | I16: =I14-I15 | J16: =J14-J15 | K16: =K14-K15 | ... M16: =M14-M15
A17: Discount factor | D17: =1/(1+Assumptions!$B$16)^(D4-0.5) | E17: =1/(1+Assumptions!$B$16)^(E4-0.5) | F17: =1/(1+Assumptions!$B$16)^(F4-0.5) | G17: =1/(1+Assumptions!$B$16)^(G4-0.5) | H17: =1/(1+Assumptions!$B$16)^(H4-0.5) | I17: =1/(1+Assumptions!$B$16)^(I4-0.5) | J17: =1/(1+Assumptions!$B$16)^(J4-0.5) | K17: =1/(1+Assumptions!$B$16)^(K4-0.5) | ... M17: =1/(1+Assumptions!$B$16)^(M4-0.5)
A18: PV ($mm) | D18: =D16*D17 | E18: =E16*E17 | F18: =F16*F17 | G18: =G16*G17 | H18: =H16*H17 | I18: =I16*I17 | J18: =J16*J17 | K18: =K16*K17 | ... M18: =M16*M17
A20: NPV ($mm) | B20: =SUM(D18:M18)

Sheet Santa Elena
A1: Santa Elena — mini-DCF
A3: Year | D3: 2026 | E3: 2027 | F3: 2028 | G3: 2029 | H3: 2030 | I3: 2031 | J3: 2032 | K3: 2033 | L3: 2034 | M3: 2035
A4: t | D4: 1 | E4: 2 | F4: 3 | G4: 4 | H4: 5 | I4: 6 | J4: 7 | K4: 8 | L4: 9 | M4: 10
A5: Active (1/0) | D5: =IF(D4<=Assumptions!$I$30,1,0) | E5: =IF(E4<=Assumptions!$I$30,1,0) | F5: =IF(F4<=Assumptions!$I$30,1,0) | G5: =IF(G4<=Assumptions!$I$30,1,0) | H5: =IF(H4<=Assumptions!$I$30,1,0) | I5: =IF(I4<=Assumptions!$I$30,1,0) | J5: =IF(J4<=Assumptions!$I$30,1,0) | K5: =IF(K4<=Assumptions!$I$30,1,0) | ... M5: =IF(M4<=Assumptions!$I$30,1,0)
A6: Ag prod (Moz) | D6: =Assumptions!$B$30*D5 | E6: =Assumptions!$B$30*E5 | F6: =Assumptions!$B$30*F5 | G6: =Assumptions!$B$30*G5 | H6: =Assumptions!$B$30*H5 | I6: =Assumptions!$B$30*I5 | J6: =Assumptions!$B$30*J5 | K6: =Assumptions!$B$30*K5 | ... M6: =Assumptions!$B$30*M5
A7: Au prod (koz) | D7: =Assumptions!$C$30*D5 | E7: =Assumptions!$C$30*E5 | F7: =Assumptions!$C$30*F5 | G7: =Assumptions!$C$30*G5 | H7: =Assumptions!$C$30*H5 | I7: =Assumptions!$C$30*I5 | J7: =Assumptions!$C$30*J5 | K7: =Assumptions!$C$30*K5 | ... M7: =Assumptions!$C$30*M5
A8: Byprod AgEq (Moz) | D8: =Assumptions!$D$30*D5 | E8: =Assumptions!$D$30*E5 | F8: =Assumptions!$D$30*F5 | G8: =Assumptions!$D$30*G5 | H8: =Assumptions!$D$30*H5 | I8: =Assumptions!$D$30*I5 | J8: =Assumptions!$D$30*J5 | K8: =Assumptions!$D$30*K5 | ... M8: =Assumptions!$D$30*M5
A9: Ag price | D9: =Assumptions!D$9 | E9: =Assumptions!E$9 | F9: =Assumptions!F$9 | G9: =Assumptions!G$9 | H9: =Assumptions!H$9 | I9: =Assumptions!I$9 | J9: =Assumptions!J$9 | K9: =Assumptions!K$9 | ... M9: =Assumptions!M$9
A10: Au price | D10: =Assumptions!D$14 | E10: =Assumptions!E$14 | F10: =Assumptions!F$14 | G10: =Assumptions!G$14 | H10: =Assumptions!H$14 | I10: =Assumptions!I$14 | J10: =Assumptions!J$14 | K10: =Assumptions!K$14 | ... M10: =Assumptions!M$14
A11: AgEq total (Moz) | D11: =D6+D7/1000*D10/D9+D8 | E11: =E6+E7/1000*E10/E9+E8 | F11: =F6+F7/1000*F10/F9+F8 | G11: =G6+G7/1000*G10/G9+G8 | H11: =H6+H7/1000*H10/H9+H8 | I11: =I6+I7/1000*I10/I9+I8 | J11: =J6+J7/1000*J10/J9+J8 | K11: =K6+K7/1000*K10/K9+K8 | ... M11: =M6+M7/1000*M10/M9+M8
A12: Revenue ($mm) | D12: =D6*D9+D7/1000*D10+D8*D9 | E12: =E6*E9+E7/1000*E10+E8*E9 | F12: =F6*F9+F7/1000*F10+F8*F9 | G12: =G6*G9+G7/1000*G10+G8*G9 | H12: =H6*H9+H7/1000*H10+H8*H9 | I12: =I6*I9+I7/1000*I10+I8*I9 | J12: =J6*J9+J7/1000*J10+J8*J9 | K12: =K6*K9+K7/1000*K10+K8*K9 | ... M12: =M6*M9+M7/1000*M10+M8*M9
A13: AISC cost ($mm) | D13: =Assumptions!$E$30*D11 | E13: =Assumptions!$E$30*E11 | F13: =Assumptions!$E$30*F11 | G13: =Assumptions!$E$30*G11 | H13: =Assumptions!$E$30*H11 | I13: =Assumptions!$E$30*I11 | J13: =Assumptions!$E$30*J11 | K13: =Assumptions!$E$30*K11 | ... M13: =Assumptions!$E$30*M11
A14: Pre-tax CF ($mm) | D14: =D12-D13 | E14: =E12-E13 | F14: =F12-F13 | G14: =G12-G13 | H14: =H12-H13 | I14: =I12-I13 | J14: =J12-J13 | K14: =K12-K13 | ... M14: =M12-M13
A15: Tax ($mm) | D15: =MAX(0,D14*Assumptions!$B$17) | E15: =MAX(0,E14*Assumptions!$B$17) | F15: =MAX(0,F14*Assumptions!$B$17) | G15: =MAX(0,G14*Assumptions!$B$17) | H15: =MAX(0,H14*Assumptions!$B$17) | I15: =MAX(0,I14*Assumptions!$B$17) | J15: =MAX(0,J14*Assumptions!$B$17) | K15: =MAX(0,K14*Assumptions!$B$17) | ... M15: =MAX(0,M14*Assumptions!$B$17)
A16: After-tax CF ($mm) | D16: =D14-D15 | E16: =E14-E15 | F16: =F14-F15 | G16: =G14-G15 | H16: =H14-H15 | I16: =I14-I15 | J16: =J14-J15 | K16: =K14-K15 | ... M16: =M14-M15
A17: Discount factor | D17: =1/(1+Assumptions!$B$16)^(D4-0.5) | E17: =1/(1+Assumptions!$B$16)^(E4-0.5) | F17: =1/(1+Assumptions!$B$16)^(F4-0.5) | G17: =1/(1+Assumptions!$B$16)^(G4-0.5) | H17: =1/(1+Assumptions!$B$16)^(H4-0.5) | I17: =1/(1+Assumptions!$B$16)^(I4-0.5) | J17: =1/(1+Assumptions!$B$16)^(J4-0.5) | K17: =1/(1+Assumptions!$B$16)^(K4-0.5) | ... M17: =1/(1+Assumptions!$B$16)^(M4-0.5)
A18: PV ($mm) | D18: =D16*D17 | E18: =E16*E17 | F18: =F16*F17 | G18: =G16*G17 | H18: =H16*H17 | I18: =I16*I17 | J18: =J16*J17 | K18: =K16*K17 | ... M18: =M16*M17
A20: NPV ($mm) | B20: =SUM(D18:M18)

Sheet Los Gatos 70
A1: Los Gatos (70%) — mini-DCF
A3: Year | D3: 2026 | E3: 2027 | F3: 2028 | G3: 2029 | H3: 2030 | I3: 2031 | J3: 2032 | K3: 2033 | L3: 2034 | M3: 2035
A4: t | D4: 1 | E4: 2 | F4: 3 | G4: 4 | H4: 5 | I4: 6 | J4: 7 | K4: 8 | L4: 9 | M4: 10
A5: Active (1/0) | D5: =IF(D4<=Assumptions!$I$31,1,0) | E5: =IF(E4<=Assumptions!$I$31,1,0) | F5: =IF(F4<=Assumptions!$I$31,1,0) | G5: =IF(G4<=Assumptions!$I$31,1,0) | H5: =IF(H4<=Assumptions!$I$31,1,0) | I5: =IF(I4<=Assumptions!$I$31,1,0) | J5: =IF(J4<=Assumptions!$I$31,1,0) | K5: =IF(K4<=Assumptions!$I$31,1,0) | ... M5: =IF(M4<=Assumptions!$I$31,1,0)
A6: Ag prod (Moz) | D6: =Assumptions!$B$31*D5 | E6: =Assumptions!$B$31*E5 | F6: =Assumptions!$B$31*F5 | G6: =Assumptions!$B$31*G5 | H6: =Assumptions!$B$31*H5 | I6: =Assumptions!$B$31*I5 | J6: =Assumptions!$B$31*J5 | K6: =Assumptions!$B$31*K5 | ... M6: =Assumptions!$B$31*M5
A7: Au prod (koz) | D7: =Assumptions!$C$31*D5 | E7: =Assumptions!$C$31*E5 | F7: =Assumptions!$C$31*F5 | G7: =Assumptions!$C$31*G5 | H7: =Assumptions!$C$31*H5 | I7: =Assumptions!$C$31*I5 | J7: =Assumptions!$C$31*J5 | K7: =Assumptions!$C$31*K5 | ... M7: =Assumptions!$C$31*M5
A8: Byprod AgEq (Moz) | D8: =Assumptions!$D$31*D5 | E8: =Assumptions!$D$31*E5 | F8: =Assumptions!$D$31*F5 | G8: =Assumptions!$D$31*G5 | H8: =Assumptions!$D$31*H5 | I8: =Assumptions!$D$31*I5 | J8: =Assumptions!$D$31*J5 | K8: =Assumptions!$D$31*K5 | ... M8: =Assumptions!$D$31*M5
A9: Ag price | D9: =Assumptions!D$9 | E9: =Assumptions!E$9 | F9: =Assumptions!F$9 | G9: =Assumptions!G$9 | H9: =Assumptions!H$9 | I9: =Assumptions!I$9 | J9: =Assumptions!J$9 | K9: =Assumptions!K$9 | ... M9: =Assumptions!M$9
A10: Au price | D10: =Assumptions!D$14 | E10: =Assumptions!E$14 | F10: =Assumptions!F$14 | G10: =Assumptions!G$14 | H10: =Assumptions!H$14 | I10: =Assumptions!I$14 | J10: =Assumptions!J$14 | K10: =Assumptions!K$14 | ... M10: =Assumptions!M$14
A11: AgEq total (Moz) | D11: =D6+D7/1000*D10/D9+D8 | E11: =E6+E7/1000*E10/E9+E8 | F11: =F6+F7/1000*F10/F9+F8 | G11: =G6+G7/1000*G10/G9+G8 | H11: =H6+H7/1000*H10/H9+H8 | I11: =I6+I7/1000*I10/I9+I8 | J11: =J6+J7/1000*J10/J9+J8 | K11: =K6+K7/1000*K10/K9+K8 | ... M11: =M6+M7/1000*M10/M9+M8
A12: Revenue ($mm) | D12: =D6*D9+D7/1000*D10+D8*D9 | E12: =E6*E9+E7/1000*E10+E8*E9 | F12: =F6*F9+F7/1000*F10+F8*F9 | G12: =G6*G9+G7/1000*G10+G8*G9 | H12: =H6*H9+H7/1000*H10+H8*H9 | I12: =I6*I9+I7/1000*I10+I8*I9 | J12: =J6*J9+J7/1000*J10+J8*J9 | K12: =K6*K9+K7/1000*K10+K8*K9 | ... M12: =M6*M9+M7/1000*M10+M8*M9
A13: AISC cost ($mm) | D13: =Assumptions!$E$31*D11 | E13: =Assumptions!$E$31*E11 | F13: =Assumptions!$E$31*F11 | G13: =Assumptions!$E$31*G11 | H13: =Assumptions!$E$31*H11 | I13: =Assumptions!$E$31*I11 | J13: =Assumptions!$E$31*J11 | K13: =Assumptions!$E$31*K11 | ... M13: =Assumptions!$E$31*M11
A14: Pre-tax CF ($mm) | D14: =D12-D13 | E14: =E12-E13 | F14: =F12-F13 | G14: =G12-G13 | H14: =H12-H13 | I14: =I12-I13 | J14: =J12-J13 | K14: =K12-K13 | ... M14: =M12-M13
A15: Tax ($mm) | D15: =MAX(0,D14*Assumptions!$B$17) | E15: =MAX(0,E14*Assumptions!$B$17) | F15: =MAX(0,F14*Assumptions!$B$17) | G15: =MAX(0,G14*Assumptions!$B$17) | H15: =MAX(0,H14*Assumptions!$B$17) | I15: =MAX(0,I14*Assumptions!$B$17) | J15: =MAX(0,J14*Assumptions!$B$17) | K15: =MAX(0,K14*Assumptions!$B$17) | ... M15: =MAX(0,M14*Assumptions!$B$17)
A16: After-tax CF ($mm) | D16: =D14-D15 | E16: =E14-E15 | F16: =F14-F15 | G16: =G14-G15 | H16: =H14-H15 | I16: =I14-I15 | J16: =J14-J15 | K16: =K14-K15 | ... M16: =M14-M15
A17: Discount factor | D17: =1/(1+Assumptions!$B$16)^(D4-0.5) | E17: =1/(1+Assumptions!$B$16)^(E4-0.5) | F17: =1/(1+Assumptions!$B$16)^(F4-0.5) | G17: =1/(1+Assumptions!$B$16)^(G4-0.5) | H17: =1/(1+Assumptions!$B$16)^(H4-0.5) | I17: =1/(1+Assumptions!$B$16)^(I4-0.5) | J17: =1/(1+Assumptions!$B$16)^(J4-0.5) | K17: =1/(1+Assumptions!$B$16)^(K4-0.5) | ... M17: =1/(1+Assumptions!$B$16)^(M4-0.5)
A18: PV ($mm) | D18: =D16*D17 | E18: =E16*E17 | F18: =F16*F17 | G18: =G16*G17 | H18: =H16*H17 | I18: =I16*I17 | J18: =J16*J17 | K18: =K16*K17 | ... M18: =M16*M17
A20: NPV ($mm) | B20: =SUM(D18:M18)

Sheet La Encantada
A1: La Encantada — mini-DCF
A3: Year | D3: 2026 | E3: 2027 | F3: 2028 | G3: 2029 | H3: 2030 | I3: 2031 | J3: 2032 | K3: 2033 | L3: 2034 | M3: 2035
A4: t | D4: 1 | E4: 2 | F4: 3 | G4: 4 | H4: 5 | I4: 6 | J4: 7 | K4: 8 | L4: 9 | M4: 10
A5: Active (1/0) | D5: =IF(D4<=Assumptions!$I$32,1,0) | E5: =IF(E4<=Assumptions!$I$32,1,0) | F5: =IF(F4<=Assumptions!$I$32,1,0) | G5: =IF(G4<=Assumptions!$I$32,1,0) | H5: =IF(H4<=Assumptions!$I$32,1,0) | I5: =IF(I4<=Assumptions!$I$32,1,0) | J5: =IF(J4<=Assumptions!$I$32,1,0) | K5: =IF(K4<=Assumptions!$I$32,1,0) | ... M5: =IF(M4<=Assumptions!$I$32,1,0)
A6: Ag prod (Moz) | D6: =Assumptions!$B$32*D5 | E6: =Assumptions!$B$32*E5 | F6: =Assumptions!$B$32*F5 | G6: =Assumptions!$B$32*G5 | H6: =Assumptions!$B$32*H5 | I6: =Assumptions!$B$32*I5 | J6: =Assumptions!$B$32*J5 | K6: =Assumptions!$B$32*K5 | ... M6: =Assumptions!$B$32*M5
A7: Au prod (koz) | D7: =Assumptions!$C$32*D5 | E7: =Assumptions!$C$32*E5 | F7: =Assumptions!$C$32*F5 | G7: =Assumptions!$C$32*G5 | H7: =Assumptions!$C$32*H5 | I7: =Assumptions!$C$32*I5 | J7: =Assumptions!$C$32*J5 | K7: =Assumptions!$C$32*K5 | ... M7: =Assumptions!$C$32*M5
A8: Byprod AgEq (Moz) | D8: =Assumptions!$D$32*D5 | E8: =Assumptions!$D$32*E5 | F8: =Assumptions!$D$32*F5 | G8: =Assumptions!$D$32*G5 | H8: =Assumptions!$D$32*H5 | I8: =Assumptions!$D$32*I5 | J8: =Assumptions!$D$32*J5 | K8: =Assumptions!$D$32*K5 | ... M8: =Assumptions!$D$32*M5
A9: Ag price | D9: =Assumptions!D$9 | E9: =Assumptions!E$9 | F9: =Assumptions!F$9 | G9: =Assumptions!G$9 | H9: =Assumptions!H$9 | I9: =Assumptions!I$9 | J9: =Assumptions!J$9 | K9: =Assumptions!K$9 | ... M9: =Assumptions!M$9
A10: Au price | D10: =Assumptions!D$14 | E10: =Assumptions!E$14 | F10: =Assumptions!F$14 | G10: =Assumptions!G$14 | H10: =Assumptions!H$14 | I10: =Assumptions!I$14 | J10: =Assumptions!J$14 | K10: =Assumptions!K$14 | ... M10: =Assumptions!M$14
A11: AgEq total (Moz) | D11: =D6+D7/1000*D10/D9+D8 | E11: =E6+E7/1000*E10/E9+E8 | F11: =F6+F7/1000*F10/F9+F8 | G11: =G6+G7/1000*G10/G9+G8 | H11: =H6+H7/1000*H10/H9+H8 | I11: =I6+I7/1000*I10/I9+I8 | J11: =J6+J7/1000*J10/J9+J8 | K11: =K6+K7/1000*K10/K9+K8 | ... M11: =M6+M7/1000*M10/M9+M8
A12: Revenue ($mm) | D12: =D6*D9+D7/1000*D10+D8*D9 | E12: =E6*E9+E7/1000*E10+E8*E9 | F12: =F6*F9+F7/1000*F10+F8*F9 | G12: =G6*G9+G7/1000*G10+G8*G9 | H12: =H6*H9+H7/1000*H10+H8*H9 | I12: =I6*I9+I7/1000*I10+I8*I9 | J12: =J6*J9+J7/1000*J10+J8*J9 | K12: =K6*K9+K7/1000*K10+K8*K9 | ... M12: =M6*M9+M7/1000*M10+M8*M9
A13: AISC cost ($mm) | D13: =Assumptions!$E$32*D11 | E13: =Assumptions!$E$32*E11 | F13: =Assumptions!$E$32*F11 | G13: =Assumptions!$E$32*G11 | H13: =Assumptions!$E$32*H11 | I13: =Assumptions!$E$32*I11 | J13: =Assumptions!$E$32*J11 | K13: =Assumptions!$E$32*K11 | ... M13: =Assumptions!$E$32*M11
A14: Pre-tax CF ($mm) | D14: =D12-D13 | E14: =E12-E13 | F14: =F12-F13 | G14: =G12-G13 | H14: =H12-H13 | I14: =I12-I13 | J14: =J12-J13 | K14: =K12-K13 | ... M14: =M12-M13
A15: Tax ($mm) | D15: =MAX(0,D14*Assumptions!$B$17) | E15: =MAX(0,E14*Assumptions!$B$17) | F15: =MAX(0,F14*Assumptions!$B$17) | G15: =MAX(0,G14*Assumptions!$B$17) | H15: =MAX(0,H14*Assumptions!$B$17) | I15: =MAX(0,I14*Assumptions!$B$17) | J15: =MAX(0,J14*Assumptions!$B$17) | K15: =MAX(0,K14*Assumptions!$B$17) | ... M15: =MAX(0,M14*Assumptions!$B$17)
A16: After-tax CF ($mm) | D16: =D14-D15 | E16: =E14-E15 | F16: =F14-F15 | G16: =G14-G15 | H16: =H14-H15 | I16: =I14-I15 | J16: =J14-J15 | K16: =K14-K15 | ... M16: =M14-M15
A17: Discount factor | D17: =1/(1+Assumptions!$B$16)^(D4-0.5) | E17: =1/(1+Assumptions!$B$16)^(E4-0.5) | F17: =1/(1+Assumptions!$B$16)^(F4-0.5) | G17: =1/(1+Assumptions!$B$16)^(G4-0.5) | H17: =1/(1+Assumptions!$B$16)^(H4-0.5) | I17: =1/(1+Assumptions!$B$16)^(I4-0.5) | J17: =1/(1+Assumptions!$B$16)^(J4-0.5) | K17: =1/(1+Assumptions!$B$16)^(K4-0.5) | ... M17: =1/(1+Assumptions!$B$16)^(M4-0.5)
A18: PV ($mm) | D18: =D16*D17 | E18: =E16*E17 | F18: =F16*F17 | G18: =G16*G17 | H18: =H16*H17 | I18: =I16*I17 | J18: =J16*J17 | K18: =K16*K17 | ... M18: =M16*M17
A20: NPV ($mm) | B20: =SUM(D18:M18)

Sheet JerrittCanyon
A1: Jerritt Canyon restart — simple case (revisit after Q4 2026 PFS)
A3: Year | D3: 2026 | E3: 2027 | F3: 2028 | G3: 2029 | H3: 2030 | I3: 2031 | J3: 2032 | K3: 2033 | L3: 2034 | M3: 2035
A4: t | D4: 1 | E4: 2 | F4: 3 | G4: 4 | H4: 5 | I4: 6 | J4: 7 | K4: 8 | L4: 9 | M4: 10
A5: Producing (1/0) | D5: =IF(AND(D3>=Assumptions!$B$37,D3<Assumptions!$B$37+Assumptions!$B$38),1,0) | E5: =IF(AND(E3>=Assumptions!$B$37,E3<Assumptions!$B$37+Assumptions!$B$38),1,0) | F5: =IF(AND(F3>=Assumptions!$B$37,F3<Assumptions!$B$37+Assumptions!$B$38),1,0) | G5: =IF(AND(G3>=Assumptions!$B$37,G3<Assumptions!$B$37+Assumptions!$B$38),1,0) | H5: =IF(AND(H3>=Assumptions!$B$37,H3<Assumptions!$B$37+Assumptions!$B$38),1,0) | I5: =IF(AND(I3>=Assumptions!$B$37,I3<Assumptions!$B$37+Assumptions!$B$38),1,0) | J5: =IF(AND(J3>=Assumptions!$B$37,J3<Assumptions!$B$37+Assumptions!$B$38),1,0) | K5: =IF(AND(K3>=Assumptions!$B$37,K3<Assumptions!$B$37+Assumptions!$B$38),1,0) | ... M5: =IF(AND(M3>=Assumptions!$B$37,M3<Assumptions!$B$37+Assumptions!$B$38),1,0)
A6: Au prod (koz) | D6: =Assumptions!$B$35*D5 | E6: =Assumptions!$B$35*E5 | F6: =Assumptions!$B$35*F5 | G6: =Assumptions!$B$35*G5 | H6: =Assumptions!$B$35*H5 | I6: =Assumptions!$B$35*I5 | J6: =Assumptions!$B$35*J5 | K6: =Assumptions!$B$35*K5 | ... M6: =Assumptions!$B$35*M5
A7: Au price | D7: =Assumptions!D$14 | E7: =Assumptions!E$14 | F7: =Assumptions!F$14 | G7: =Assumptions!G$14 | H7: =Assumptions!H$14 | I7: =Assumptions!I$14 | J7: =Assumptions!J$14 | K7: =Assumptions!K$14 | ... M7: =Assumptions!M$14
A8: Margin $/oz (Au price - AISC) | D8: =D7-Assumptions!$B$36 | E8: =E7-Assumptions!$B$36 | F8: =F7-Assumptions!$B$36 | G8: =G7-Assumptions!$B$36 | H8: =H7-Assumptions!$B$36 | I8: =I7-Assumptions!$B$36 | J8: =J7-Assumptions!$B$36 | K8: =K7-Assumptions!$B$36 | ... M8: =M7-Assumptions!$B$36
A9: Operating CF ($mm) | D9: =D6*D8/1000 | E9: =E6*E8/1000 | F9: =F6*F8/1000 | G9: =G6*G8/1000 | H9: =H6*H8/1000 | I9: =I6*I8/1000 | J9: =J6*J8/1000 | K9: =K6*K8/1000 | ... M9: =M6*M8/1000
A10: Restart capex ($mm) | D10: =Assumptions!$B$39 | E10: =Assumptions!$B$40 | F10: 0 | G10: 0 | H10: 0 | I10: 0 | J10: 0 | K10: 0 | L10: 0 | M10: 0
A11: Pre-tax CF ($mm) | D11: =D9-D10 | E11: =E9-E10 | F11: =F9-F10 | G11: =G9-G10 | H11: =H9-H10 | I11: =I9-I10 | J11: =J9-J10 | K11: =K9-K10 | ... M11: =M9-M10
A12: Tax ($mm) | D12: =MAX(0,D11*Assumptions!$B$18) | E12: =MAX(0,E11*Assumptions!$B$18) | F12: =MAX(0,F11*Assumptions!$B$18) | G12: =MAX(0,G11*Assumptions!$B$18) | H12: =MAX(0,H11*Assumptions!$B$18) | I12: =MAX(0,I11*Assumptions!$B$18) | J12: =MAX(0,J11*Assumptions!$B$18) | K12: =MAX(0,K11*Assumptions!$B$18) | ... M12: =MAX(0,M11*Assumptions!$B$18)
A13: After-tax CF ($mm) | D13: =D11-D12 | E13: =E11-E12 | F13: =F11-F12 | G13: =G11-G12 | H13: =H11-H12 | I13: =I11-I12 | J13: =J11-J12 | K13: =K11-K12 | ... M13: =M11-M12
A14: Discount factor | D14: =1/(1+Assumptions!$B$16)^(D4-0.5) | E14: =1/(1+Assumptions!$B$16)^(E4-0.5) | F14: =1/(1+Assumptions!$B$16)^(F4-0.5) | G14: =1/(1+Assumptions!$B$16)^(G4-0.5) | H14: =1/(1+Assumptions!$B$16)^(H4-0.5) | I14: =1/(1+Assumptions!$B$16)^(I4-0.5) | J14: =1/(1+Assumptions!$B$16)^(J4-0.5) | K14: =1/(1+Assumptions!$B$16)^(K4-0.5) | ... M14: =1/(1+Assumptions!$B$16)^(M4-0.5)
A15: PV ($mm) | D15: =D13*D14 | E15: =E13*E14 | F15: =F13*F14 | G15: =G13*G14 | H15: =H13*H14 | I15: =I13*I14 | J15: =J13*J14 | K15: =K13*K14 | ... M15: =M13*M14
A17: NPV ($mm) | B17: =SUM(D15:M15)
